{
  "root": "tmp/",
  "entrypoint": "index.html",
  "fragments": [],
  "sources": [
    "scripts/@catalyst-elements/*/demo/**",
    "scripts/@catalyst-elements/*/dist/**"
  ],
  "extraDependencies": [
    "scripts/@webcomponents/webcomponentsjs/[!gulpfile]*.js",
    "scripts/@webcomponents/shadycss/[!gulpfile]*.js",
    "analysis.json"
  ],
  "builds": [{
    "name": "docs",
    "bundle": false,
    "js": {
      "compile": false,
      "minify": false
    },
    "css": {
      "minify": false
    },
    "html": {
      "minify": false
    },
    "addServiceWorker": false,
    "addPushManifest": false,
    "insertPrefetchLinks": false
  }]
}
